{
    "name": "Croconaw",
    "fillerinfo": "Big Jaw Pokemon-1.1-25.0",
    "dex": 159,
    "type": ["Water", "Water"],
    "evolutions": ["Feraligatr"],
    "evolutionsLVL": [30],
    "forms": [],
    "mega": [],
    "stats": [65, 80, 80, 59, 63, 58],
    "ev": [0, 1, 1, 0, 0, 0],
    "moves": ["Leer", "Scratch", "Water Gun", "Rage", "Bite", "Scary Face", "Ice Fang", "Flail", "Crunch", "Chip Away", "Slash", "Screech", "Thrash", "Aqua Tail", "Superpower", "Hydro Pump"],
    "movesLVL": [1, 1, 1, 8, 13, 15, 21, 24, 30, 33, 39, 42, 48, 51, 57, 60],
    "movesTM": [1, 2, 5, 6, 7, 10, 13, 14, 17, 18, 21, 27, 31, 32, 39, 40, 42, 44, 45, 48, 55, 56, 65, 75, 80, 87, 88, 90, 94, 98, 100],
    "movesTR": [],
    "abilities": ["Torrent", "Sheer Force"],
    "growthrate": "Medium_Slow",
    "exp": 142,
    "normalURL": "https://archives.bulbagarden.net/media/upload/thumb/a/a5/159Croconaw.png/600px-159Croconaw.png",
    "shinyURL": "https://images-wixmp-ed30a86b8c4ca887773594c2.wixmp.com/i/e48d6b9d-3b1d-46a0-a254-3a448ec3a8a5/ddif79c-d05e7e57-cfd6-46de-b90d-ab2c577a8057.png/v1/fill/w_894,h_894,strp/_159_croconaw_by_tonofdirt726_ddif79c-pre.png"
}