{
    "name": "Politoed",
    "fillerinfo": "Frog Pokemon-1.1-33.9",
    "dex": 186,
    "type": ["Water", "Water"],
    "evolutions": [],
    "evolutionsLVL": [],
    "forms": [],
    "mega": [],
    "stats": [90, 75, 75, 90, 100, 70],
    "ev": [0, 0, 0, 0, 3, 0],
    "moves": ["Bubble Beam", "Double Slap", "Perish Song", "Hypnosis", "Swagger", "Bounce", "Hyper Voice"],
    "movesLVL": [1, 1, 1, 1, 27, 37, 48],
    "movesTM": [6, 7, 10, 13, 14, 15, 17, 18, 21, 26, 27, 29, 31, 32, 42, 44, 45, 46, 48, 49, 52, 55, 56, 66, 68, 78, 87, 88, 90, 94, 98, 100],
    "movesTR": [1, 3, 4, 5, 6, 10, 11, 14, 16, 20, 26, 27, 30, 35, 42, 45, 64, 67, 84, 98],
    "abilities": ["Water Absorb", "Damp", "Drizzle"],
    "growthrate": "Medium_Slow",
    "exp": 225,
    "normalURL": "https://archives.bulbagarden.net/media/upload/thumb/a/a4/186Politoed.png/600px-186Politoed.png",
    "shinyURL": "https://images-wixmp-ed30a86b8c4ca887773594c2.wixmp.com/i/e48d6b9d-3b1d-46a0-a254-3a448ec3a8a5/ddiimkt-236b806e-da63-4829-b316-28dadc61be3a.png/v1/fill/w_894,h_894,strp/_186_politoed_by_tonofdirt726_ddiimkt-pre.png"
}