{
    "name": "Donphan",
    "fillerinfo": "Armor Pokemon-1.1-120.0",
    "dex": 232,
    "type": ["Ground", "Ground"],
    "evolutions": [],
    "evolutionsLVL": [],
    "forms": [],
    "mega": [],
    "stats": [90, 120, 120, 60, 60, 50],
    "ev": [0, 1, 1, 0, 0, 0],
    "moves": ["Fury Attack", "Fire Fang", "Defense Curl", "Bulldoze", "Growl", "Thunder Fang", "Horn Attack", "Rapid Spin", "Rollout", "Assurance", "Knock Off", "Slam", "Magnitude", "Scary Face", "Earthquake", "Giga Impact"],
    "movesLVL": [0, 1, 1, 1, 1, 1, 1, 6, 10, 15, 19, 24, 30, 37, 43, 50],
    "movesTM": [5, 6, 10, 11, 15, 17, 21, 26, 27, 32, 37, 39, 42, 44, 45, 48, 49, 59, 68, 69, 71, 74, 78, 80, 84, 87, 88, 90, 100],
    "movesTR": [],
    "abilities": ["Sturdy", "Sand Veil"],
    "growthrate": "Medium_Fast",
    "exp": 175,
    "normalURL": "https://archives.bulbagarden.net/media/upload/thumb/5/53/232Donphan.png/600px-232Donphan.png",
    "shinyURL": "https://images-wixmp-ed30a86b8c4ca887773594c2.wixmp.com/i/e48d6b9d-3b1d-46a0-a254-3a448ec3a8a5/ddivmb8-2ee6c9a4-19d2-4d05-be22-9399abdf1a38.png/v1/fill/w_852,h_852,strp/_232_donphan_by_tonofdirt726_ddivmb8-fullview.png"
}