{
    "name": "Silicobra",
    "fillerinfo": "Sand Snake Pokemon-2.2-7.6",
    "dex": 843,
    "type": ["Ground", "Ground"],
    "evolutions": ["Sandaconda"],
    "evolutionsLVL": [36],
    "forms": [],
    "mega": [],
    "stats": [52, 57, 75, 35, 50, 46],
    "ev": [0, 0, 1, 0, 0, 0],
    "moves": ["Wrap", "Sand Attack", "Minimize", "Brutal Swing", "Bulldoze", "Headbutt", "Glare", "Dig", "Sandstorm", "Slam", "Coil", "Sand Tomb"],
    "movesLVL": [1, 1, 5, 10, 15, 20, 25, 30, 35, 40, 45, 50],
    "movesTM": [],
    "movesTR": [10, 20, 26, 27, 67, 87],
    "abilities": ["Sand Spit", "Shed Skin", "Sand Veil"],
    "growthrate": "Medium_Fast",
    "exp": 63,
    "normalURL": "https://archives.bulbagarden.net/media/upload/b/b5/843Silicobra.png",
    "shinyURL": "https://images-wixmp-ed30a86b8c4ca887773594c2.wixmp.com/i/e48d6b9d-3b1d-46a0-a254-3a448ec3a8a5/ddqayc7-d7989e00-6c79-4b39-b0dd-1a0b1e8d4f16.png"
}