{
    "name": "Falinks",
    "fillerinfo": "Formation Pokemon-3.0-62.0",
    "dex": 870,
    "type": ["Fighting", "Fighting"],
    "evolutions": [],
    "evolutionsLVL": [],
    "forms": [],
    "mega": [],
    "stats": [65, 100, 100, 70, 60, 75],
    "ev": [0, 2, 0, 0, 1, 0],
    "moves": ["Protect", "Tackle", "Rock Smash", "Focus Energy", "Headbutt", "Bulk Up", "Endure", "Reversal", "First Impression", "No Retreat", "Iron Defense", "Close Combat", "Megahorn", "Counter"],
    "movesLVL": [1, 1, 5, 10, 15, 20, 25, 30, 35, 40, 45, 50, 55, 60],
    "movesTM": [],
    "movesTR": [0, 12, 13, 20, 21, 26, 27, 28, 39, 46, 48, 53, 57, 64, 69, 74, 95],
    "abilities": ["Battle Armor", "Defiant"],
    "growthrate": "Medium_Fast",
    "exp": 165,
    "normalURL": "https://archives.bulbagarden.net/media/upload/b/bb/870Falinks.png",
    "shinyURL": "https://images-wixmp-ed30a86b8c4ca887773594c2.wixmp.com/i/e48d6b9d-3b1d-46a0-a254-3a448ec3a8a5/ddxrw4m-9164503c-8849-4fc5-b019-4c25c55db906.png/v1/fill/w_894,h_894,strp/_870_falinks_by_tonofdirt726_ddxrw4m-pre.png"
}