{
    "name": "Zamazenta",
    "fillerinfo": "Warrior Pokemon-2.9-785.0",
    "dex": 889,
    "type": ["Fighting", "Steel"],
    "evolutions": [],
    "evolutionsLVL": [],
    "forms": [],
    "mega": [],
    "stats": [92, 130, 145, 80, 145, 128],
    "ev": [0, 0, 0, 0, 0, 3],
    "moves": ["Bite", "Howl", "Metal Burst", "Metal Claw", "Quick Attack", "Wide Guard", "Slash", "Iron Defense", "Iron Head", "Laser Focus", "Crunch", "Moonblast", "Close Combat", "Giga Impact", "Behemoth Bash"],
    "movesLVL": [1, 1, 1, 1, 1, 1, 11, 22, 33, 44, 55, 66, 77, 88, 99],
    "movesTM": [],
    "movesTR": [12, 13, 20, 21, 26, 27, 31, 32, 42, 46, 53, 64, 70, 74, 85, 86, 90, 92, 97],
    "abilities": ["Dauntless Shield"],
    "growthrate": "Slow",
    "exp": 360,
    "normalURL": "https://archives.bulbagarden.net/media/upload/thumb/7/72/889Zamazenta.png/600px-889Zamazenta.png",
    "shinyURL": "https://images-wixmp-ed30a86b8c4ca887773594c2.wixmp.com/i/e48d6b9d-3b1d-46a0-a254-3a448ec3a8a5/ddy8y2d-8bb6d24c-16a4-49e4-a426-70c313f13844.png/v1/fill/w_894,h_894,strp/_889_zamazenta__crowned_shield__by_tonofdirt726_ddy8y2d-pre.png"
}
