{
    "name": "Type-Null-",
    "fillerinfo": "じんこうポケモン-1.9-120.5",
    "dex": 772,
    "type": ["Normal", "Normal"],
    "evolutions": [],
    "evolutionsLVL": [],
    "forms": [],
    "mega": [],
    "stats": [95, 95, 95, 95, 95, 59],
    "ev": [2, 0, 0, 0, 0, 0],
    "moves": ["Tackle", "Rage", "Pursuit", "Imprison", "Aerial Ace", "Crush Claw", "Scary Face", "X Scissor", "Take Down", "Metal Sound", "Iron Head", "Double Hit", "Air Slash", "Punishment", "Razor Wind", "Tri Attack", "Double Edge", "Heal Block"],
    "movesLVL": [1, 5, 10, 15, 20, 25, 30, 35, 40, 45, 50, 55, 60, 65, 70, 75, 80, 85],
    "movesTM": [1, 2, 5, 6, 7, 10, 11, 17, 18, 21, 27, 32, 37, 40, 42, 43, 44, 48, 65, 66, 68, 73, 75, 80, 81, 87, 88, 89, 90, 100],
    "movesTR": [0, 19, 20, 26, 27, 46, 47, 60, 74, 85],
    "abilities": ["Battle Armor"],
    "growthrate": "Slow",
    "exp": 107,
    "normalURL": "",
    "shinyURL": ""
}