{
    "name": "Oshawott",
    "fillerinfo": "Sea Otter Pokemon-0.5-5.9",
    "dex": 501,
    "type": ["Water", "Water"],
    "evolutions": ["Dewott", "Samurott"],
    "evolutionsLVL": [17, 36],
    "forms": [],
    "mega": [],
    "stats": [55, 55, 45, 63, 45, 45],
    "ev": [0, 0, 0, 1, 0, 0],
    "moves": ["Tackle", "Tail Whip", "Water Gun", "Water Sport", "Focus Energy", "Razor Shell", "Fury Cutter", "Water Pulse", "Revenge", "Aqua Jet", "Encore", "Aqua Tail", "Retaliate", "Swords Dance", "Hydro Pump"],
    "movesLVL": [1, 5, 7, 11, 13, 17, 19, 23, 25, 29, 31, 35, 37, 41, 43],
    "movesTM": [1, 6, 7, 10, 12, 13, 14, 17, 18, 21, 27, 32, 40, 42, 44, 45, 48, 54, 55, 56, 75, 81, 86, 87, 88, 90, 94, 98, 100],
    "movesTR": [],
    "abilities": ["Torrent", "Shell Armor"],
    "growthrate": "Medium_Slow",
    "exp": 62,
    "normalURL": "https://archives.bulbagarden.net/media/upload/thumb/3/3b/501Oshawott.png/600px-501Oshawott.png",
    "shinyURL": "https://images-wixmp-ed30a86b8c4ca887773594c2.wixmp.com/i/e48d6b9d-3b1d-46a0-a254-3a448ec3a8a5/ddkbipd-708f0a25-9784-4909-b47c-fa12aa41fc02.png/v1/fill/w_894,h_894,strp/_501_oshawott_by_tonofdirt726_ddkbipd-pre.png"
}